pymport.py
pymport-0.0.7.dist-info/licenses/LICENSE
pymport-0.0.7.dist-info/METADATA
pymport-0.0.7.dist-info/WHEEL
pymport-0.0.7.dist-info/entry_points.txt
pymport-0.0.7.dist-info/top_level.txt
pymport-0.0.7.dist-info/RECORD
