Metadata-Version: 2.4
Name: pymport
Version: 0.0.7
Summary: A lightweight Python linter for checking unused imports.
Author: malatorrediaz
Author-email: rmoralespp <rmoralespp@gmail.com>
Project-URL: Source, https://github.com/rmoralespp/pymport
Project-URL: Homepage, https://github.com/rmoralespp/pymport
Project-URL: Changelog, https://github.com/rmoralespp/pymport/blob/main/CHANGELOG.md
Project-URL: Issues, https://github.com/rmoralespp/pymport/issues
Keywords: python,linter,developer-tools,code-quality,import
Classifier: Programming Language :: Python :: 3
Classifier: Programming Language :: Python :: 3 :: Only
Classifier: Programming Language :: Python :: 3.12
Classifier: Programming Language :: Python :: 3.13
Classifier: Programming Language :: Python :: 3.14
Classifier: Intended Audience :: Developers
Classifier: Intended Audience :: Information Technology
Classifier: Topic :: Software Development :: Libraries :: Python Modules
Classifier: Topic :: Internet
Classifier: Topic :: Utilities
Classifier: Topic :: Documentation
Classifier: Topic :: Software Development :: Quality Assurance
Requires-Python: >=3.12
License-File: LICENSE
Dynamic: license-file
